fancywidgets/__init__.py
fancywidgets/tests.py
fancywidgets/media/__init__.py
fancywidgets/media/__init__.pyc
fancywidgets/media/__init__.pyo
fancywidgets/media/icons/foundation-icon-fonts-3/README
fancywidgets/media/icons/foundation-icon-fonts-3/README~
fancywidgets/media/icons/foundation-icon-fonts-3/fi-address-book.svg
fancywidgets/media/icons/foundation-icon-fonts-3/fi-alert.svg
fancywidgets/media/icons/foundation-icon-fonts-3/fi-align-center.svg
fancywidgets/media/icons/foundation-icon-fonts-3/fi-align-justify.svg
fancywidgets/media/icons/foundation-icon-fonts-3/fi-align-left.svg
fancywidgets/media/icons/foundation-icon-fonts-3/fi-align-right.svg
fancywidgets/media/icons/foundation-icon-fonts-3/fi-anchor.svg
fancywidgets/media/icons/foundation-icon-fonts-3/fi-annotate.svg
fancywidgets/media/icons/foundation-icon-fonts-3/fi-archive.svg
fancywidgets/media/icons/foundation-icon-fonts-3/fi-arrow-down.svg
fancywidgets/media/icons/foundation-icon-fonts-3/fi-arrow-left.svg
fancywidgets/media/icons/foundation-icon-fonts-3/fi-arrow-right.svg
fancywidgets/media/icons/foundation-icon-fonts-3/fi-arrow-up.svg
fancywidgets/media/icons/foundation-icon-fonts-3/fi-arrows-compress.svg
fancywidgets/media/icons/foundation-icon-fonts-3/fi-arrows-expand.svg
fancywidgets/media/icons/foundation-icon-fonts-3/fi-arrows-in.svg
fancywidgets/media/icons/foundation-icon-fonts-3/fi-arrows-out.svg
fancywidgets/media/icons/foundation-icon-fonts-3/fi-asl.svg
fancywidgets/media/icons/foundation-icon-fonts-3/fi-asterisk.svg
fancywidgets/media/icons/foundation-icon-fonts-3/fi-at-sign.svg
fancywidgets/media/icons/foundation-icon-fonts-3/fi-background-color.svg
fancywidgets/media/icons/foundation-icon-fonts-3/fi-battery-empty.svg
fancywidgets/media/icons/foundation-icon-fonts-3/fi-battery-full.svg
fancywidgets/media/icons/foundation-icon-fonts-3/fi-battery-half.svg
fancywidgets/media/icons/foundation-icon-fonts-3/fi-bitcoin-circle.svg
fancywidgets-0.2.5.dist-info/DESCRIPTION.rst
fancywidgets-0.2.5.dist-info/METADATA
fancywidgets-0.2.5.dist-info/RECORD
fancywidgets-0.2.5.dist-info/WHEEL
fancywidgets-0.2.5.dist-info/metadata.json
fancywidgets-0.2.5.dist-info/top_level.txt
