Metadata-Version: 2.0
Name: fancywidgets
Version: 0.2.5
Summary: 
Requires-Dist: fancytools
Requires-Dist: pkginfo
